atheris_no_libfuzzer.py
ubsan_with_fuzzer.so
asan_with_fuzzer.so
libclang_rt.fuzzer_no_main.a
ubsan_cxx_with_fuzzer.so
atheris/instrument_bytecode.py
atheris/custom_mutator_and_crossover_fuzz_test.py
atheris/pyinstaller_coverage_test.py
atheris/import_hook.py
atheris/version_dependent.py
atheris/fuzzed_data_provider_test.py
atheris/coverage_test.py
atheris/core_without_libfuzzer.cpython-36m-x86_64-linux-gnu.so
atheris/custom_crossover.cpython-36m-x86_64-linux-gnu.so
atheris/native.cpython-36m-x86_64-linux-gnu.so
atheris/custom_mutator.cpython-36m-x86_64-linux-gnu.so
atheris/utils.py
atheris/fuzz_test_lib.py
atheris/core_with_libfuzzer.cpython-36m-x86_64-linux-gnu.so
atheris/custom_mutator_fuzz_test.py
atheris/regex_match_generation_test.py
atheris/function_hooks.py
atheris/fuzz_test.py
atheris/__init__.py
atheris/hook-atheris.py
atheris/custom_crossover_fuzz_test.py
atheris/coverage_g3test.py
atheris/coverage_test_helper.py
atheris-2.3.0.dist-info/WHEEL
atheris-2.3.0.dist-info/RECORD
atheris-2.3.0.dist-info/top_level.txt
atheris-2.3.0.dist-info/LICENSE
atheris-2.3.0.dist-info/entry_points.txt
atheris-2.3.0.dist-info/METADATA
