Metadata-Version: 2.1
Name: atheris
Version: 2.3.0
Summary: A coverage-guided fuzzer for Python and Python extensions.
Home-page: https://github.com/google/atheris/
Author: Bitshift
Author-email: atheris@google.com
License: UNKNOWN
Platform: UNKNOWN
License-File: LICENSE
